jnews_mcp_server/__init__.py
jnews_mcp_server/__main__.py
jnews_mcp_server/server.py
mseep_jnews_mcp_server-0.1.6.dist-info/METADATA
mseep_jnews_mcp_server-0.1.6.dist-info/WHEEL
mseep_jnews_mcp_server-0.1.6.dist-info/entry_points.txt
mseep_jnews_mcp_server-0.1.6.dist-info/top_level.txt
mseep_jnews_mcp_server-0.1.6.dist-info/RECORD
